rtl/Multiplier.v
module Multiplier (
    input [31:0] rowA, 
    input [31:0] colB, 
    output signed [16:0] result
);

    wire signed[7:0] a0= rowA[0  +: 8];
    wire signed[7:0] a1= rowA[8  +: 8];
    wire signed[7:0] a2= rowA[16 +: 8];
    wire signed[7:0] a3= rowA[24 +: 8];

    wire signed[7:0] b0= colB[0  +: 8];
    wire signed[7:0] b1= colB[8  +: 8];
    wire signed[7:0] b2= colB[16 +: 8];
    wire signed[7:0] b3= colB[24 +: 8];

    assign result = (a0*b0) + (a1*b1) + (a2*b2) + (a3*b3);

endmodule

rtl/Matrix_Multiplier.v
`timescale 1ns/10ps

module Matrix_Multiplier (
    input[7:0] din, input wrt_en, input rst, input clk, output reg[16:0]  dout
);
    
    localparam IDLE=0, LOAD=1, CALC=2, OUT=3;
    reg[1:0] next_state, state;

    reg signed[7:0] matA[0:15], matB[0:15];
    wire signed[31:0] row0, row1, row2, row3;
    wire signed[31:0] colB;
    wire signed[16:0] res0, res1, res2, res3;
    reg signed[16:0] matR[0:15];
    wire signed[7:0] sign_din;

    reg[4:0] loadcount;
    reg[1:0] col;
    reg[3:0] outcount;
    integer i;

    always @(*) begin
        case (state)
            IDLE:   next_state= (wrt_en)? LOAD:IDLE;
            LOAD:   next_state= (loadcount==31)? CALC:LOAD;
            CALC:   next_state= (col==3)? OUT:CALC;
            OUT:    next_state= (outcount==15)? IDLE:OUT;
        endcase
    end

    always @(posedge clk) begin
        if (rst) 
            {state,loadcount,col,outcount}<=13'b0;
        else begin
            state<= next_state;

            if (state==LOAD && loadcount==0) begin
                for (i=0; i<16; i=i+1) 
                    matR[i]<= 17'b0;
            end
        end
    end

    always @(posedge clk) begin
        if (state==LOAD) begin
            loadcount<= loadcount+1'b1;
        end else if (state==CALC) begin
            col<= col+1;
        end else if (state==OUT) begin
            outcount<=outcount+1;
        end else
            {loadcount,col,outcount}<= 11'b0;
    end

    always @(posedge clk) begin
        if (state==LOAD) begin
            if (loadcount<=5'd15)
                matA[loadcount[3:0]]<= sign_din;
            else
                matB[loadcount-16]<= sign_din;
        end else if (state==CALC) begin
            matR[0*4+col]<= res0;
            matR[1*4+col]<= res1;
            matR[2*4+col]<= res2;
            matR[3*4+col]<= res3;
        end else if (state==OUT) 
            dout<= (matR[outcount]>=0)? {1'b0,matR[outcount][15:0]} : {1'b1,~(matR[outcount][15:0]-1'b1)};
    end

    

    assign row0= {matA[0*4+0],matA[0*4+1],matA[0*4+2],matA[0*4+3]};
    assign row1= {matA[1*4+0],matA[1*4+1],matA[1*4+2],matA[1*4+3]};
    assign row2= {matA[2*4+0],matA[2*4+1],matA[2*4+2],matA[2*4+3]};
    assign row3= {matA[3*4+0],matA[3*4+1],matA[3*4+2],matA[3*4+3]};

    assign colB= {matB[0*4+col],matB[1*4+col],matB[2*4+col],matB[3*4+col]};

    Multiplier i0 (.rowA(row0),
                   .colB(colB),
                   .result(res0));
    Multiplier i1 (.rowA(row1),
                   .colB(colB),
                   .result(res1));
    Multiplier i2 (.rowA(row2),
                   .colB(colB),
                   .result(res2));
    Multiplier i3 (.rowA(row3),
                   .colB(colB),
                   .result(res3));


    assign sign_din= (din[7])? -$signed({1'b0,din[6:0]}) : $signed({1'b0,din[6:0]});


endmodule

tb/Matrix_Multiplier_tb.v
`timescale 1ns/10ps

module Matrix_Multiplier_tb;
    reg[7:0] din;
    reg wrt_en, rst, clk;
    wire[16:0] dout;

    reg signed[7:0] matIn[31:0];
    reg signed[16:0] matExpect[15:0];
    reg [1023:0] input_file;

    Matrix_Multiplier instance_1(.din(din),
                    .wrt_en(wrt_en),
                    .rst(rst),
                    .clk(clk),
                    .dout(dout));

    initial begin
        clk=0;
        forever #5 clk=~clk;
    end

    initial begin
        $dumpfile("wave.vcd");
        $dumpvars(0, Matrix_Multiplier_tb);
    end

    initial begin
        if (!$value$plusargs("INPUT=%s", input_file))
            input_file = "min.hex";

        $display("INFO: loading %0s", input_file);
        $readmemh(input_file, matIn);
    end

    initial begin
        #1000;
        $display("INFO: timeout reached, finishing simulation.");
        $finish;
    end

    task reset_dut;
        begin
            rst=1;
            wrt_en=0;
            din=8'b0;
        end
    endtask

    task input_load;
        integer i;
        begin
            wrt_en=1;

            @(posedge clk);

            for (i=0; i<32; i=i+1) begin
                @(negedge clk);
                din= S2CtoS(matIn[i]);
            end
            wrt_en=0;
        end
    endtask

    task calc_expect;
        integer r,c,k;
        reg signed[16:0] sum;
        begin
            for (r=0; r<4; r=r+1) begin
                for (c=0; c<4; c=c+1) begin
                    sum= 17'b0;
                    for (k=0; k<4; k=k+1) begin
                        sum= sum + matIn[r*4+k]*matIn[k*4+c+16];
                    end
                    matExpect[r*4+c]= sum;
                end
            end
        end
    endtask


    task check_dout;
        integer i, pass;
        begin
            pass=0;
            for (i=0;i <16; i=i+1) begin
                @(posedge clk);
                #1;
                if (StoS2C(dout)!==matExpect[i]) 
                    $display("%0d expected %0d got %0d.",i,matExpect[i],StoS2C(dout));
                else
                    pass= pass+1;
            end
            $display("%0d/16 passed!",pass);
        end
    endtask

    function [16:0] StoS2C;
        input[16:0] sign;
        begin
            StoS2C= (sign[16])? -$signed({1'b0,sign[15:0]}) : $signed({1'b0,sign[15:0]});
        end
    endfunction

    function [7:0] S2CtoS;
        input signed[7:0] S2C;
        begin
            S2CtoS= (S2C>=0)? {1'b0,S2C[6:0]} : {1'b1,~(S2C[6:0]-1'b1)};
        end
    endfunction

    initial begin
        reset_dut();

        #10 rst=0;
        input_load();

        calc_expect();

        wait(instance_1.state==2'b11);
        $display("Start OUT at %0t",$time);
        check_dout();

        $display("INFO: simulation complete.");
        $finish;
    end


endmodule

sim/wave.vcd
$date
	Wed Jun 10 21:07:18 2026
$end
$version
	Icarus Verilog
$end
$timescale
	10ps
$end
$scope module Matrix_Multiplier_tb $end
$var wire 17 ! dout [16:0] $end
$var reg 1 " clk $end
$var reg 8 # din [7:0] $end
$var reg 1024 $ input_file [1023:0] $end
$var reg 1 % rst $end
$var reg 1 & wrt_en $end
$scope function S2CtoS $end
$var reg 8 ' S2C [7:0] $end
$var reg 8 ( S2CtoS [7:0] $end
$upscope $end
$scope function StoS2C $end
$var reg 17 ) StoS2C [16:0] $end
$var reg 17 * sign [16:0] $end
$upscope $end
$scope module instance_1 $end
$var wire 1 + clk $end
$var wire 32 , colB [31:0] $end
$var wire 8 - din [7:0] $end
$var wire 17 . res0 [16:0] $end
$var wire 17 / res1 [16:0] $end
$var wire 17 0 res2 [16:0] $end
$var wire 17 1 res3 [16:0] $end
$var wire 32 2 row0 [31:0] $end
$var wire 32 3 row1 [31:0] $end
$var wire 32 4 row2 [31:0] $end
$var wire 32 5 row3 [31:0] $end
$var wire 1 6 rst $end
$var wire 8 7 sign_din [7:0] $end
$var wire 1 8 wrt_en $end
$var reg 2 9 col [1:0] $end
$var reg 17 : dout [16:0] $end
$var integer 32 ; i [31:0] $end
$var reg 5 < loadcount [4:0] $end
$var reg 2 = next_state [1:0] $end
$var reg 4 > outcount [3:0] $end
$var reg 2 ? state [1:0] $end
$scope module i0 $end
$var wire 8 @ a0 [7:0] $end
$var wire 8 A a1 [7:0] $end
$var wire 8 B a2 [7:0] $end
$var wire 8 C a3 [7:0] $end
$var wire 8 D b0 [7:0] $end
$var wire 8 E b1 [7:0] $end
$var wire 8 F b2 [7:0] $end
$var wire 8 G b3 [7:0] $end
$var wire 32 H colB [31:0] $end
$var wire 17 I result [16:0] $end
$var wire 32 J rowA [31:0] $end
$upscope $end
$scope module i1 $end
$var wire 8 K a0 [7:0] $end
$var wire 8 L a1 [7:0] $end
$var wire 8 M a2 [7:0] $end
$var wire 8 N a3 [7:0] $end
$var wire 8 O b0 [7:0] $end
$var wire 8 P b1 [7:0] $end
$var wire 8 Q b2 [7:0] $end
$var wire 8 R b3 [7:0] $end
$var wire 32 S colB [31:0] $end
$var wire 17 T result [16:0] $end
$var wire 32 U rowA [31:0] $end
$upscope $end
$scope module i2 $end
$var wire 8 V a0 [7:0] $end
$var wire 8 W a1 [7:0] $end
$var wire 8 X a2 [7:0] $end
$var wire 8 Y a3 [7:0] $end
$var wire 8 Z b0 [7:0] $end
$var wire 8 [ b1 [7:0] $end
$var wire 8 \ b2 [7:0] $end
$var wire 8 ] b3 [7:0] $end
$var wire 32 ^ colB [31:0] $end
$var wire 17 _ result [16:0] $end
$var wire 32 ` rowA [31:0] $end
$upscope $end
$scope module i3 $end
$var wire 8 a a0 [7:0] $end
$var wire 8 b a1 [7:0] $end
$var wire 8 c a2 [7:0] $end
$var wire 8 d a3 [7:0] $end
$var wire 8 e b0 [7:0] $end
$var wire 8 f b1 [7:0] $end
$var wire 8 g b2 [7:0] $end
$var wire 8 h b3 [7:0] $end
$var wire 32 i colB [31:0] $end
$var wire 17 j result [16:0] $end
$var wire 32 k rowA [31:0] $end
$upscope $end
$upscope $end
$scope task calc_expect $end
$var integer 32 l c [31:0] $end
$var integer 32 m k [31:0] $end
$var integer 32 n r [31:0] $end
$var reg 17 o sum [16:0] $end
$upscope $end
$scope task check_dout $end
$var integer 32 p i [31:0] $end
$var integer 32 q pass [31:0] $end
$upscope $end
$scope task input_load $end
$var integer 32 r i [31:0] $end
$upscope $end
$scope task reset_dut $end
$upscope $end
$upscope $end
$enddefinitions $end
#0
$dumpvars
bx r
bx q
bx p
bx o
bx n
bx m
bx l
bz k
bx j
bx i
bx h
bx g
bx f
bx e
bz d
bz c
bz b
bz a
bz `
bx _
bx ^
bx ]
bx \
bx [
bx Z
bz Y
bz X
bz W
bz V
bz U
bx T
bx S
bx R
bx Q
bx P
bx O
bz N
bz M
bz L
bz K
bz J
bx I
bx H
bx G
bx F
bx E
bx D
bz C
bz B
bz A
bz @
bx ?
bx >
bx =
bx <
bx ;
bx :
bx 9
08
b0 7
16
bz 5
bz 4
bz 3
bz 2
bx 1
bx 0
bx /
bx .
b0 -
bx ,
0+
bx *
bx )
bx (
bx '
0&
1%
b11010010110111001110000011101010111010000101111011000100110000101110011011010010110001101011111011100000110111101110011011010010111010001101001011101100110010100101110011010000110010101111000 $
b0 #
0"
bx !
$end
#500
b0 =
b0 ?
b0 <
b0 9
b0 >
1"
1+
#1000
b1 =
0"
0+
1&
18
0%
06
#1500
b1 ?
b0 r
1"
1+
#2000
b1 r
b0 (
b0 '
0"
0+
#2500
bx @
bx A
bx B
b0 C
b1 <
b0xxxxxxxxxxxxxxxxxxxxxxxx 2
b0xxxxxxxxxxxxxxxxxxxxxxxx J
b10000 ;
1"
1+
#3000
b1 7
b10 r
b1 #
b1 -
b1 (
b1 '
0"
0+
#3500
b1 B
b1xxxxxxxxxxxxxxxx 2
b1xxxxxxxxxxxxxxxx J
b10 <
1"
1+
#4000
b10 7
b11 r
b10 #
b10 -
b10 (
b10 '
0"
0+
#4500
b10 A
b11 <
b100000010xxxxxxxx 2
b100000010xxxxxxxx J
1"
1+
#5000
b11 7
b100 r
b11 #
b11 -
b11 (
b11 '
0"
0+
#5500
b11 @
b10000001000000011 2
b10000001000000011 J
b100 <
1"
1+
#6000
b100 7
b101 r
b100 #
b100 -
b100 (
b100 '
0"
0+
#6500
bx K
bx L
bx M
b100 N
b101 <
b100xxxxxxxxxxxxxxxxxxxxxxxx 3
b100xxxxxxxxxxxxxxxxxxxxxxxx U
1"
1+
#7000
b101 7
b110 r
b101 #
b101 -
b101 (
b101 '
0"
0+
#7500
b101 M
b10000000101xxxxxxxxxxxxxxxx 3
b10000000101xxxxxxxxxxxxxxxx U
b110 <
1"
1+
#8000
b110 7
b111 r
b110 #
b110 -
b110 (
b110 '
0"
0+
#8500
b110 L
b111 <
b1000000010100000110xxxxxxxx 3
b1000000010100000110xxxxxxxx U
1"
1+
#9000
b111 7
b1000 r
b111 #
b111 -
b111 (
b111 '
0"
0+
#9500
b111 K
b100000001010000011000000111 3
b100000001010000011000000111 U
b1000 <
1"
1+
#10000
b1000 7
b1001 r
b1000 #
b1000 -
b1000 (
b1000 '
0"
0+
#10500
bx V
bx W
bx X
b1000 Y
b1001 <
b1000xxxxxxxxxxxxxxxxxxxxxxxx 4
b1000xxxxxxxxxxxxxxxxxxxxxxxx `
1"
1+
#11000
b1001 7
b1010 r
b1001 #
b1001 -
b1001 (
b1001 '
0"
0+
#11500
b1001 X
b100000001001xxxxxxxxxxxxxxxx 4
b100000001001xxxxxxxxxxxxxxxx `
b1010 <
1"
1+
#12000
b1010 7
b1011 r
b1010 #
b1010 -
b1010 (
b1010 '
0"
0+
#12500
b1010 W
b1011 <
b10000000100100001010xxxxxxxx 4
b10000000100100001010xxxxxxxx `
1"
1+
#13000
b1011 7
b1100 r
b1011 #
b1011 -
b1011 (
b1011 '
0"
0+
#13500
b1011 V
b1000000010010000101000001011 4
b1000000010010000101000001011 `
b1100 <
1"
1+
#14000
b1100 7
b1101 r
b1100 #
b1100 -
b1100 (
b1100 '
0"
0+
#14500
bx a
bx b
bx c
b1100 d
b1101 <
b1100xxxxxxxxxxxxxxxxxxxxxxxx 5
b1100xxxxxxxxxxxxxxxxxxxxxxxx k
1"
1+
#15000
b1101 7
b1110 r
b1101 #
b1101 -
b1101 (
b1101 '
0"
0+
#15500
b1101 c
b110000001101xxxxxxxxxxxxxxxx 5
b110000001101xxxxxxxxxxxxxxxx k
b1110 <
1"
1+
#16000
b1110 7
b1111 r
b1110 #
b1110 -
b1110 (
b1110 '
0"
0+
#16500
b1110 b
b1111 <
b11000000110100001110xxxxxxxx 5
b11000000110100001110xxxxxxxx k
1"
1+
#17000
b1111 7
b10000 r
b1111 #
b1111 -
b1111 (
b1111 '
0"
0+
#17500
b1111 a
b1100000011010000111000001111 5
b1100000011010000111000001111 k
b10000 <
1"
1+
#18000
b0 7
b10001 r
b0 #
b0 -
b0 (
b0 '
0"
0+
#18500
b0 G
b0 R
b0 ]
b0 h
b10001 <
b0xxxxxxxxxxxxxxxxxxxxxxxx ,
b0xxxxxxxxxxxxxxxxxxxxxxxx H
b0xxxxxxxxxxxxxxxxxxxxxxxx S
b0xxxxxxxxxxxxxxxxxxxxxxxx ^
b0xxxxxxxxxxxxxxxxxxxxxxxx i
1"
1+
#19000
b1 7
b10010 r
b1 #
b1 -
b1 (
b1 '
0"
0+
#19500
b10010 <
1"
1+
#20000
b10 7
b10011 r
b10 #
b10 -
b10 (
b10 '
0"
0+
#20500
b10011 <
1"
1+
#21000
b11 7
b10100 r
b11 #
b11 -
b11 (
b11 '
0"
0+
#21500
b10100 <
1"
1+
#22000
b100 7
b10101 r
b100 #
b100 -
b100 (
b100 '
0"
0+
#22500
b100 F
b100 Q
b100 \
b100 g
b10101 <
b100xxxxxxxxxxxxxxxx ,
b100xxxxxxxxxxxxxxxx H
b100xxxxxxxxxxxxxxxx S
b100xxxxxxxxxxxxxxxx ^
b100xxxxxxxxxxxxxxxx i
1"
1+
#23000
b101 7
b10110 r
b101 #
b101 -
b101 (
b101 '
0"
0+
#23500
b10110 <
1"
1+
#24000
b110 7
b10111 r
b110 #
b110 -
b110 (
b110 '
0"
0+
#24500
b10111 <
1"
1+
#25000
b111 7
b11000 r
b111 #
b111 -
b111 (
b111 '
0"
0+
#25500
b11000 <
1"
1+
#26000
b1000 7
b11001 r
b1000 #
b1000 -
b1000 (
b1000 '
0"
0+
#26500
b1000 E
b1000 P
b1000 [
b1000 f
b11001 <
b10000001000xxxxxxxx ,
b10000001000xxxxxxxx H
b10000001000xxxxxxxx S
b10000001000xxxxxxxx ^
b10000001000xxxxxxxx i
1"
1+
#27000
b1001 7
b11010 r
b1001 #
b1001 -
b1001 (
b1001 '
0"
0+
#27500
b11010 <
1"
1+
#28000
b1010 7
b11011 r
b1010 #
b1010 -
b1010 (
b1010 '
0"
0+
#28500
b11011 <
1"
1+
#29000
b1011 7
b11100 r
b1011 #
b1011 -
b1011 (
b1011 '
0"
0+
#29500
b11100 <
1"
1+
#30000
b1100 7
b11101 r
b1100 #
b1100 -
b1100 (
b1100 '
0"
0+
#30500
b111000 .
b111000 I
b1100 D
b10011000 /
b10011000 T
b1100 O
b11111000 0
b11111000 _
b1100 Z
b101011000 1
b101011000 j
b1100 e
b11101 <
b1000000100000001100 ,
b1000000100000001100 H
b1000000100000001100 S
b1000000100000001100 ^
b1000000100000001100 i
1"
1+
#31000
b1101 7
b11110 r
b1101 #
b1101 -
b1101 (
b1101 '
0"
0+
#31500
b11110 <
1"
1+
#32000
b1110 7
b11111 r
b1110 #
b1110 -
b1110 (
b1110 '
0"
0+
#32500
b10 =
b11111 <
1"
1+
#33000
b1111 7
b100 m
b111111010 o
b100 l
b100 n
0&
08
b100000 r
b1111 #
b1111 -
b1111 (
b1111 '
0"
0+
#33500
b0 <
b10 ?
1"
1+
#34000
0"
0+
#34500
b1 G
b1 R
b1 ]
b1 h
b101 F
b101 Q
b101 \
b101 g
b1001 E
b1001 P
b1001 [
b1001 f
b111110 .
b111110 I
b1101 D
b10101110 /
b10101110 T
b1101 O
b100011110 0
b100011110 _
b1101 Z
b110001110 1
b110001110 j
b1101 e
b1 9
b1000001010000100100001101 ,
b1000001010000100100001101 H
b1000001010000100100001101 S
b1000001010000100100001101 ^
b1000001010000100100001101 i
1"
1+
#35000
0"
0+
#35500
b10 G
b10 R
b10 ]
b10 h
b110 F
b110 Q
b110 \
b110 g
b1010 E
b1010 P
b1010 [
b1010 f
b1000100 .
b1000100 I
b1110 D
b11000100 /
b11000100 T
b1110 O
b101000100 0
b101000100 _
b1110 Z
b111000100 1
b111000100 j
b1110 e
b10 9
b10000001100000101000001110 ,
b10000001100000101000001110 H
b10000001100000101000001110 S
b10000001100000101000001110 ^
b10000001100000101000001110 i
1"
1+
#36000
0"
0+
#36500
b11 =
b11 G
b11 R
b11 ]
b11 h
b111 F
b111 Q
b111 \
b111 g
b1011 E
b1011 P
b1011 [
b1011 f
b1001010 .
b1001010 I
b1111 D
b11011010 /
b11011010 T
b1111 O
b101101010 0
b101101010 _
b1111 Z
b111111010 1
b111111010 j
b1111 e
b11 9
b11000001110000101100001111 ,
b11000001110000101100001111 H
b11000001110000101100001111 S
b11000001110000101100001111 ^
b11000001110000101100001111 i
1"
1+
#37000
0"
0+
#37500
b0 G
b0 R
b0 ]
b0 h
b100 F
b100 Q
b100 \
b100 g
b1000 E
b1000 P
b1000 [
b1000 f
b111000 .
b111000 I
b1100 D
b10011000 /
b10011000 T
b1100 O
b11111000 0
b11111000 _
b1100 Z
b101011000 1
b101011000 j
b1100 e
b0 p
b0 q
b0 9
b1000000100000001100 ,
b1000000100000001100 H
b1000000100000001100 S
b1000000100000001100 ^
b1000000100000001100 i
b11 ?
1"
1+
#38000
0"
0+
#38500
b1 >
b111000 :
b111000 !
1"
1+
#38600
b1 p
b1 q
b111000 )
b111000 *
#39000
0"
0+
#39500
b111110 :
b111110 !
b10 >
1"
1+
#39600
b10 p
b10 q
b111110 )
b111110 *
#40000
0"
0+
#40500
b11 >
b1000100 :
b1000100 !
1"
1+
#40600
b11 p
b11 q
b1000100 )
b1000100 *
#41000
0"
0+
#41500
b1001010 :
b1001010 !
b100 >
1"
1+
#41600
b100 p
b100 q
b1001010 )
b1001010 *
#42000
0"
0+
#42500
b101 >
b10011000 :
b10011000 !
1"
1+
#42600
b101 p
b101 q
b10011000 )
b10011000 *
#43000
0"
0+
#43500
b10101110 :
b10101110 !
b110 >
1"
1+
#43600
b110 p
b110 q
b10101110 )
b10101110 *
#44000
0"
0+
#44500
b111 >
b11000100 :
b11000100 !
1"
1+
#44600
b111 p
b111 q
b11000100 )
b11000100 *
#45000
0"
0+
#45500
b11011010 :
b11011010 !
b1000 >
1"
1+
#45600
b1000 p
b1000 q
b11011010 )
b11011010 *
#46000
0"
0+
#46500
b1001 >
b11111000 :
b11111000 !
1"
1+
#46600
b1001 p
b1001 q
b11111000 )
b11111000 *
#47000
0"
0+
#47500
b100011110 :
b100011110 !
b1010 >
1"
1+
#47600
b1010 p
b1010 q
b100011110 )
b100011110 *
#48000
0"
0+
#48500
b1011 >
b101000100 :
b101000100 !
1"
1+
#48600
b1011 p
b1011 q
b101000100 )
b101000100 *
#49000
0"
0+
#49500
b101101010 :
b101101010 !
b1100 >
1"
1+
#49600
b1100 p
b1100 q
b101101010 )
b101101010 *
#50000
0"
0+
#50500
b1101 >
b101011000 :
b101011000 !
1"
1+
#50600
b1101 p
b1101 q
b101011000 )
b101011000 *
#51000
0"
0+
#51500
b110001110 :
b110001110 !
b1110 >
1"
1+
#51600
b1110 p
b1110 q
b110001110 )
b110001110 *
#52000
0"
0+
#52500
b0 =
b1111 >
b111000100 :
b111000100 !
1"
1+
#52600
b1111 p
b1111 q
b111000100 )
b111000100 *
#53000
0"
0+
#53500
b111111010 :
b111111010 !
b0 >
b0 ?
1"
1+
#53600
b10000 p
b10000 q
b111111010 )
b111111010 *
