rtl/Multiplier.v
module Multiplier (
    input [31:0] rowA, 
    input [31:0] colB, 
    output signed [16:0] result
);

    wire signed[7:0] a0= rowA[0  +: 8];
    wire signed[7:0] a1= rowA[8  +: 8];
    wire signed[7:0] a2= rowA[16 +: 8];
    wire signed[7:0] a3= rowA[24 +: 8];

    wire signed[7:0] b0= colB[0  +: 8];
    wire signed[7:0] b1= colB[8  +: 8];
    wire signed[7:0] b2= colB[16 +: 8];
    wire signed[7:0] b3= colB[24 +: 8];

    assign result = (a0*b0) + (a1*b1) + (a2*b2) + (a3*b3);

endmodule

rtl/Matrix_Multiplier.v
`timescale 1ns/10ps

module Matrix_Multiplier (
    input[7:0] din, input wrt_en, input rst, input clk, output reg[16:0]  dout, output done
);
    
    localparam IDLE=0, LOAD=1, CALC=2, OUT=3;
    reg[1:0] next_state, state;

    reg signed[7:0] matA[0:15], matB[0:15];
    wire signed[31:0] row0, row1, row2, row3;
    wire signed[31:0] colB;
    wire signed[16:0] res0, res1, res2, res3;
    reg signed[16:0] matR[0:15];
    wire signed[7:0] sign_din;

    reg[4:0] loadcount;
    reg[1:0] col;
    reg[3:0] outcount;
    integer i;

    always @(*) begin
        case (state)
            IDLE:   next_state= (wrt_en)? LOAD:IDLE;
            LOAD:   next_state= (loadcount==31)? CALC:LOAD;
            CALC:   next_state= (col==3)? OUT:CALC;
            OUT:    next_state= (outcount==15)? IDLE:OUT;
        endcase
    end

    always @(posedge clk) begin
        if (rst) 
            {state,loadcount,col,outcount}<=13'b0;
        else begin
            state<= next_state;

            if (state==LOAD && loadcount==0) begin
                for (i=0; i<16; i=i+1) 
                    matR[i]<= 17'b0;
            end
        end
    end

    always @(posedge clk) begin
        if (state==LOAD) begin
            loadcount<= loadcount+1'b1;
        end else if (state==CALC) begin
            col<= col+1;
        end else if (state==OUT) begin
            outcount<=outcount+1;
        end else
            {loadcount,col,outcount}<= 11'b0;
    end

    always @(posedge clk) begin
        if (state==LOAD) begin
            if (loadcount<=5'd15)
                matA[loadcount[3:0]]<= sign_din;
            else
                matB[loadcount-16]<= sign_din;
        end else if (state==CALC) begin
            matR[0*4+col]<= res0;
            matR[1*4+col]<= res1;
            matR[2*4+col]<= res2;
            matR[3*4+col]<= res3;
        end else if (state==OUT) 
            dout<= (matR[outcount]>=0)? {1'b0,matR[outcount][15:0]} : {1'b1,~(matR[outcount][15:0]-1'b1)};
    end

    

    assign row0= {matA[0*4+0],matA[0*4+1],matA[0*4+2],matA[0*4+3]};
    assign row1= {matA[1*4+0],matA[1*4+1],matA[1*4+2],matA[1*4+3]};
    assign row2= {matA[2*4+0],matA[2*4+1],matA[2*4+2],matA[2*4+3]};
    assign row3= {matA[3*4+0],matA[3*4+1],matA[3*4+2],matA[3*4+3]};

    assign colB= {matB[0*4+col],matB[1*4+col],matB[2*4+col],matB[3*4+col]};

    Multiplier i0 (.rowA(row0),
                   .colB(colB),
                   .result(res0));
    Multiplier i1 (.rowA(row1),
                   .colB(colB),
                   .result(res1));
    Multiplier i2 (.rowA(row2),
                   .colB(colB),
                   .result(res2));
    Multiplier i3 (.rowA(row3),
                   .colB(colB),
                   .result(res3));


    assign sign_din= (din[7])? -$signed({1'b0,din[6:0]}) : $signed({1'b0,din[6:0]});
    assign done= (state==OUT);


endmodule

tb/Matrix_Multiplier_tb.v
`timescale 1ns/100ps

module Matrix_Multiplier_tb;
    reg[7:0] din;
    reg wrt_en, rst, clk;
    wire done;
    wire[16:0] dout;

    reg signed[7:0] matIn[31:0];
    reg signed[16:0] matExpect[15:0];
    reg [1023:0] input_file;

    Matrix_Multiplier instance_1(.din(din),
                    .wrt_en(wrt_en),
                    .rst(rst),
                    .clk(clk),
                    .done(done),
                    .dout(dout));

    initial begin
        clk=0;
        forever #5 clk=~clk;
    end

    initial begin
        $dumpfile("wave.vcd");
        $dumpvars(0, Matrix_Multiplier_tb);
    end

    initial begin
        if (!$value$plusargs("INPUT=%s", input_file))
            input_file= "input/basic_positive.hex";
        $display("Loaded %0s", input_file);
        $readmemh(input_file, matIn, 0, 31);
    end

    initial begin
        #1000;
        $display("Timeout reached!");
        $finish;
    end

    task reset_dut;
        begin
            rst=1;
            wrt_en=0;
            din=8'b0;
        end
    endtask

    task input_load;
        integer i;
        begin
            wrt_en=1;

            @(posedge clk);

            for (i=0; i<32; i=i+1) begin
                @(negedge clk);
                din= S2CtoS(matIn[i]);
            end
            wrt_en=0;
        end
    endtask

    task calc_expect;
        integer r,c,k;
        reg signed[16:0] sum;
        begin
            for (r=0; r<4; r=r+1) begin
                for (c=0; c<4; c=c+1) begin
                    sum= 17'b0;
                    for (k=0; k<4; k=k+1) begin
                        sum= sum + matIn[r*4+k]*matIn[k*4+c+16];
                    end
                    matExpect[r*4+c]= sum;
                end
            end
        end
    endtask


    task check_dout;
        integer i, pass;
        begin
            pass=0;
            for (i=0;i <16; i=i+1) begin
                @(posedge clk);
                #1;
                if (StoS2C(dout)!==matExpect[i]) 
                    $display("%0d expected %0d got %0d.",i,matExpect[i],StoS2C(dout));
                else
                    pass= pass+1;
            end
            $display("%0d/16 passed!",pass);
        end
    endtask

    function [16:0] StoS2C;
        input[16:0] sign;
        begin
            StoS2C= (sign[16])? -$signed({1'b0,sign[15:0]}) : $signed({1'b0,sign[15:0]});
        end
    endfunction

    function [7:0] S2CtoS;
        input signed[7:0] S2C;
        begin
            S2CtoS= (S2C>=0)? {1'b0,S2C[6:0]} : {1'b1,~(S2C[6:0]-1'b1)};
        end
    endfunction

    initial begin
        reset_dut();

        #10 rst=0;
        input_load();

        calc_expect();

        wait(done);
        check_dout();

        $display("Simulation complete.");
        $finish;
    end


endmodule

sim/wave.vcd
$date
	Sat Jun 13 20:26:22 2026
$end
$version
	Icarus Verilog
$end
$timescale
	10ps
$end
$scope module Matrix_Multiplier_tb $end
$var wire 1 ! done $end
$var wire 17 " dout [16:0] $end
$var reg 1 # clk $end
$var reg 8 $ din [7:0] $end
$var reg 1024 % input_file [1023:0] $end
$var reg 1 & rst $end
$var reg 1 ' wrt_en $end
$scope function S2CtoS $end
$var reg 8 ( S2C [7:0] $end
$var reg 8 ) S2CtoS [7:0] $end
$upscope $end
$scope function StoS2C $end
$var reg 17 * StoS2C [16:0] $end
$var reg 17 + sign [16:0] $end
$upscope $end
$scope module instance_1 $end
$var wire 1 , clk $end
$var wire 32 - colB [31:0] $end
$var wire 8 . din [7:0] $end
$var wire 1 ! done $end
$var wire 17 / res0 [16:0] $end
$var wire 17 0 res1 [16:0] $end
$var wire 17 1 res2 [16:0] $end
$var wire 17 2 res3 [16:0] $end
$var wire 32 3 row0 [31:0] $end
$var wire 32 4 row1 [31:0] $end
$var wire 32 5 row2 [31:0] $end
$var wire 32 6 row3 [31:0] $end
$var wire 1 7 rst $end
$var wire 8 8 sign_din [7:0] $end
$var wire 1 9 wrt_en $end
$var reg 2 : col [1:0] $end
$var reg 17 ; dout [16:0] $end
$var integer 32 < i [31:0] $end
$var reg 5 = loadcount [4:0] $end
$var reg 2 > next_state [1:0] $end
$var reg 4 ? outcount [3:0] $end
$var reg 2 @ state [1:0] $end
$scope module i0 $end
$var wire 8 A a0 [7:0] $end
$var wire 8 B a1 [7:0] $end
$var wire 8 C a2 [7:0] $end
$var wire 8 D a3 [7:0] $end
$var wire 8 E b0 [7:0] $end
$var wire 8 F b1 [7:0] $end
$var wire 8 G b2 [7:0] $end
$var wire 8 H b3 [7:0] $end
$var wire 32 I colB [31:0] $end
$var wire 17 J result [16:0] $end
$var wire 32 K rowA [31:0] $end
$upscope $end
$scope module i1 $end
$var wire 8 L a0 [7:0] $end
$var wire 8 M a1 [7:0] $end
$var wire 8 N a2 [7:0] $end
$var wire 8 O a3 [7:0] $end
$var wire 8 P b0 [7:0] $end
$var wire 8 Q b1 [7:0] $end
$var wire 8 R b2 [7:0] $end
$var wire 8 S b3 [7:0] $end
$var wire 32 T colB [31:0] $end
$var wire 17 U result [16:0] $end
$var wire 32 V rowA [31:0] $end
$upscope $end
$scope module i2 $end
$var wire 8 W a0 [7:0] $end
$var wire 8 X a1 [7:0] $end
$var wire 8 Y a2 [7:0] $end
$var wire 8 Z a3 [7:0] $end
$var wire 8 [ b0 [7:0] $end
$var wire 8 \ b1 [7:0] $end
$var wire 8 ] b2 [7:0] $end
$var wire 8 ^ b3 [7:0] $end
$var wire 32 _ colB [31:0] $end
$var wire 17 ` result [16:0] $end
$var wire 32 a rowA [31:0] $end
$upscope $end
$scope module i3 $end
$var wire 8 b a0 [7:0] $end
$var wire 8 c a1 [7:0] $end
$var wire 8 d a2 [7:0] $end
$var wire 8 e a3 [7:0] $end
$var wire 8 f b0 [7:0] $end
$var wire 8 g b1 [7:0] $end
$var wire 8 h b2 [7:0] $end
$var wire 8 i b3 [7:0] $end
$var wire 32 j colB [31:0] $end
$var wire 17 k result [16:0] $end
$var wire 32 l rowA [31:0] $end
$upscope $end
$upscope $end
$scope task calc_expect $end
$var integer 32 m c [31:0] $end
$var integer 32 n k [31:0] $end
$var integer 32 o r [31:0] $end
$var reg 17 p sum [16:0] $end
$upscope $end
$scope task check_dout $end
$var integer 32 q i [31:0] $end
$var integer 32 r pass [31:0] $end
$upscope $end
$scope task input_load $end
$var integer 32 s i [31:0] $end
$upscope $end
$scope task reset_dut $end
$upscope $end
$upscope $end
$enddefinitions $end
#0
$dumpvars
bx s
bx r
bx q
bx p
bx o
bx n
bx m
bz l
bx k
bx j
bx i
bx h
bx g
bx f
bz e
bz d
bz c
bz b
bz a
bx `
bx _
bx ^
bx ]
bx \
bx [
bz Z
bz Y
bz X
bz W
bz V
bx U
bx T
bx S
bx R
bx Q
bx P
bz O
bz N
bz M
bz L
bz K
bx J
bx I
bx H
bx G
bx F
bx E
bz D
bz C
bz B
bz A
bx @
bx ?
bx >
bx =
bx <
bx ;
bx :
09
b0 8
17
bz 6
bz 5
bz 4
bz 3
bx 2
bx 1
bx 0
bx /
b0 .
bx -
0,
bx +
bx *
bx )
bx (
0'
1&
b11010010110111001110000011101010111010000101111011000100110000101110011011010010110001101011111011100000110111101110011011010010111010001101001011101100110010100101110011010000110010101111000 %
b0 $
0#
bx "
x!
$end
#500
b0 >
b0 @
0!
b0 =
b0 :
b0 ?
1#
1,
#1000
b1 >
0#
0,
1'
19
0&
07
#1500
b1 @
b0 s
1#
1,
#2000
b1 s
b0 )
b0 (
0#
0,
#2500
bx A
bx B
bx C
b0 D
b1 =
b0xxxxxxxxxxxxxxxxxxxxxxxx 3
b0xxxxxxxxxxxxxxxxxxxxxxxx K
b10000 <
1#
1,
#3000
b1 8
b10 s
b1 $
b1 .
b1 )
b1 (
0#
0,
#3500
b1 C
b1xxxxxxxxxxxxxxxx 3
b1xxxxxxxxxxxxxxxx K
b10 =
1#
1,
#4000
b10 8
b11 s
b10 $
b10 .
b10 )
b10 (
0#
0,
#4500
b10 B
b11 =
b100000010xxxxxxxx 3
b100000010xxxxxxxx K
1#
1,
#5000
b11 8
b100 s
b11 $
b11 .
b11 )
b11 (
0#
0,
#5500
b11 A
b10000001000000011 3
b10000001000000011 K
b100 =
1#
1,
#6000
b100 8
b101 s
b100 $
b100 .
b100 )
b100 (
0#
0,
#6500
bx L
bx M
bx N
b100 O
b101 =
b100xxxxxxxxxxxxxxxxxxxxxxxx 4
b100xxxxxxxxxxxxxxxxxxxxxxxx V
1#
1,
#7000
b101 8
b110 s
b101 $
b101 .
b101 )
b101 (
0#
0,
#7500
b101 N
b10000000101xxxxxxxxxxxxxxxx 4
b10000000101xxxxxxxxxxxxxxxx V
b110 =
1#
1,
#8000
b110 8
b111 s
b110 $
b110 .
b110 )
b110 (
0#
0,
#8500
b110 M
b111 =
b1000000010100000110xxxxxxxx 4
b1000000010100000110xxxxxxxx V
1#
1,
#9000
b111 8
b1000 s
b111 $
b111 .
b111 )
b111 (
0#
0,
#9500
b111 L
b100000001010000011000000111 4
b100000001010000011000000111 V
b1000 =
1#
1,
#10000
b1000 8
b1001 s
b1000 $
b1000 .
b1000 )
b1000 (
0#
0,
#10500
bx W
bx X
bx Y
b1000 Z
b1001 =
b1000xxxxxxxxxxxxxxxxxxxxxxxx 5
b1000xxxxxxxxxxxxxxxxxxxxxxxx a
1#
1,
#11000
b1001 8
b1010 s
b1001 $
b1001 .
b1001 )
b1001 (
0#
0,
#11500
b1001 Y
b100000001001xxxxxxxxxxxxxxxx 5
b100000001001xxxxxxxxxxxxxxxx a
b1010 =
1#
1,
#12000
b1010 8
b1011 s
b1010 $
b1010 .
b1010 )
b1010 (
0#
0,
#12500
b1010 X
b1011 =
b10000000100100001010xxxxxxxx 5
b10000000100100001010xxxxxxxx a
1#
1,
#13000
b1011 8
b1100 s
b1011 $
b1011 .
b1011 )
b1011 (
0#
0,
#13500
b1011 W
b1000000010010000101000001011 5
b1000000010010000101000001011 a
b1100 =
1#
1,
#14000
b1100 8
b1101 s
b1100 $
b1100 .
b1100 )
b1100 (
0#
0,
#14500
bx b
bx c
bx d
b1100 e
b1101 =
b1100xxxxxxxxxxxxxxxxxxxxxxxx 6
b1100xxxxxxxxxxxxxxxxxxxxxxxx l
1#
1,
#15000
b1101 8
b1110 s
b1101 $
b1101 .
b1101 )
b1101 (
0#
0,
#15500
b1101 d
b110000001101xxxxxxxxxxxxxxxx 6
b110000001101xxxxxxxxxxxxxxxx l
b1110 =
1#
1,
#16000
b1110 8
b1111 s
b1110 $
b1110 .
b1110 )
b1110 (
0#
0,
#16500
b1110 c
b1111 =
b11000000110100001110xxxxxxxx 6
b11000000110100001110xxxxxxxx l
1#
1,
#17000
b1111 8
b10000 s
b1111 $
b1111 .
b1111 )
b1111 (
0#
0,
#17500
b1111 b
b1100000011010000111000001111 6
b1100000011010000111000001111 l
b10000 =
1#
1,
#18000
b0 8
b10001 s
b0 $
b0 .
b0 )
b0 (
0#
0,
#18500
b0 H
b0 S
b0 ^
b0 i
b10001 =
b0xxxxxxxxxxxxxxxxxxxxxxxx -
b0xxxxxxxxxxxxxxxxxxxxxxxx I
b0xxxxxxxxxxxxxxxxxxxxxxxx T
b0xxxxxxxxxxxxxxxxxxxxxxxx _
b0xxxxxxxxxxxxxxxxxxxxxxxx j
1#
1,
#19000
b1 8
b10010 s
b1 $
b1 .
b1 )
b1 (
0#
0,
#19500
b10010 =
1#
1,
#20000
b10 8
b10011 s
b10 $
b10 .
b10 )
b10 (
0#
0,
#20500
b10011 =
1#
1,
#21000
b11 8
b10100 s
b11 $
b11 .
b11 )
b11 (
0#
0,
#21500
b10100 =
1#
1,
#22000
b100 8
b10101 s
b100 $
b100 .
b100 )
b100 (
0#
0,
#22500
b100 G
b100 R
b100 ]
b100 h
b10101 =
b100xxxxxxxxxxxxxxxx -
b100xxxxxxxxxxxxxxxx I
b100xxxxxxxxxxxxxxxx T
b100xxxxxxxxxxxxxxxx _
b100xxxxxxxxxxxxxxxx j
1#
1,
#23000
b101 8
b10110 s
b101 $
b101 .
b101 )
b101 (
0#
0,
#23500
b10110 =
1#
1,
#24000
b110 8
b10111 s
b110 $
b110 .
b110 )
b110 (
0#
0,
#24500
b10111 =
1#
1,
#25000
b111 8
b11000 s
b111 $
b111 .
b111 )
b111 (
0#
0,
#25500
b11000 =
1#
1,
#26000
b1000 8
b11001 s
b1000 $
b1000 .
b1000 )
b1000 (
0#
0,
#26500
b1000 F
b1000 Q
b1000 \
b1000 g
b11001 =
b10000001000xxxxxxxx -
b10000001000xxxxxxxx I
b10000001000xxxxxxxx T
b10000001000xxxxxxxx _
b10000001000xxxxxxxx j
1#
1,
#27000
b1001 8
b11010 s
b1001 $
b1001 .
b1001 )
b1001 (
0#
0,
#27500
b11010 =
1#
1,
#28000
b1010 8
b11011 s
b1010 $
b1010 .
b1010 )
b1010 (
0#
0,
#28500
b11011 =
1#
1,
#29000
b1011 8
b11100 s
b1011 $
b1011 .
b1011 )
b1011 (
0#
0,
#29500
b11100 =
1#
1,
#30000
b1100 8
b11101 s
b1100 $
b1100 .
b1100 )
b1100 (
0#
0,
#30500
b111000 /
b111000 J
b1100 E
b10011000 0
b10011000 U
b1100 P
b11111000 1
b11111000 `
b1100 [
b101011000 2
b101011000 k
b1100 f
b11101 =
b1000000100000001100 -
b1000000100000001100 I
b1000000100000001100 T
b1000000100000001100 _
b1000000100000001100 j
1#
1,
#31000
b1101 8
b11110 s
b1101 $
b1101 .
b1101 )
b1101 (
0#
0,
#31500
b11110 =
1#
1,
#32000
b1110 8
b11111 s
b1110 $
b1110 .
b1110 )
b1110 (
0#
0,
#32500
b10 >
b11111 =
1#
1,
#33000
b1111 8
b100 n
b111111010 p
b100 m
b100 o
0'
09
b100000 s
b1111 $
b1111 .
b1111 )
b1111 (
0#
0,
#33500
b0 =
b10 @
1#
1,
#34000
0#
0,
#34500
b1 H
b1 S
b1 ^
b1 i
b101 G
b101 R
b101 ]
b101 h
b1001 F
b1001 Q
b1001 \
b1001 g
b111110 /
b111110 J
b1101 E
b10101110 0
b10101110 U
b1101 P
b100011110 1
b100011110 `
b1101 [
b110001110 2
b110001110 k
b1101 f
b1 :
b1000001010000100100001101 -
b1000001010000100100001101 I
b1000001010000100100001101 T
b1000001010000100100001101 _
b1000001010000100100001101 j
1#
1,
#35000
0#
0,
#35500
b10 H
b10 S
b10 ^
b10 i
b110 G
b110 R
b110 ]
b110 h
b1010 F
b1010 Q
b1010 \
b1010 g
b1000100 /
b1000100 J
b1110 E
b11000100 0
b11000100 U
b1110 P
b101000100 1
b101000100 `
b1110 [
b111000100 2
b111000100 k
b1110 f
b10 :
b10000001100000101000001110 -
b10000001100000101000001110 I
b10000001100000101000001110 T
b10000001100000101000001110 _
b10000001100000101000001110 j
1#
1,
#36000
0#
0,
#36500
b11 >
b11 H
b11 S
b11 ^
b11 i
b111 G
b111 R
b111 ]
b111 h
b1011 F
b1011 Q
b1011 \
b1011 g
b1001010 /
b1001010 J
b1111 E
b11011010 0
b11011010 U
b1111 P
b101101010 1
b101101010 `
b1111 [
b111111010 2
b111111010 k
b1111 f
b11 :
b11000001110000101100001111 -
b11000001110000101100001111 I
b11000001110000101100001111 T
b11000001110000101100001111 _
b11000001110000101100001111 j
1#
1,
#37000
0#
0,
#37500
b0 H
b0 S
b0 ^
b0 i
b100 G
b100 R
b100 ]
b100 h
b1000 F
b1000 Q
b1000 \
b1000 g
b111000 /
b111000 J
b1100 E
b10011000 0
b10011000 U
b1100 P
b11111000 1
b11111000 `
b1100 [
b101011000 2
b101011000 k
b1100 f
b0 q
b0 r
b0 :
b1000000100000001100 -
b1000000100000001100 I
b1000000100000001100 T
b1000000100000001100 _
b1000000100000001100 j
b11 @
1!
1#
1,
#38000
0#
0,
#38500
b1 ?
b111000 ;
b111000 "
1#
1,
#38600
b1 q
b1 r
b111000 *
b111000 +
#39000
0#
0,
#39500
b111110 ;
b111110 "
b10 ?
1#
1,
#39600
b10 q
b10 r
b111110 *
b111110 +
#40000
0#
0,
#40500
b11 ?
b1000100 ;
b1000100 "
1#
1,
#40600
b11 q
b11 r
b1000100 *
b1000100 +
#41000
0#
0,
#41500
b1001010 ;
b1001010 "
b100 ?
1#
1,
#41600
b100 q
b100 r
b1001010 *
b1001010 +
#42000
0#
0,
#42500
b101 ?
b10011000 ;
b10011000 "
1#
1,
#42600
b101 q
b101 r
b10011000 *
b10011000 +
#43000
0#
0,
#43500
b10101110 ;
b10101110 "
b110 ?
1#
1,
#43600
b110 q
b110 r
b10101110 *
b10101110 +
#44000
0#
0,
#44500
b111 ?
b11000100 ;
b11000100 "
1#
1,
#44600
b111 q
b111 r
b11000100 *
b11000100 +
#45000
0#
0,
#45500
b11011010 ;
b11011010 "
b1000 ?
1#
1,
#45600
b1000 q
b1000 r
b11011010 *
b11011010 +
#46000
0#
0,
#46500
b1001 ?
b11111000 ;
b11111000 "
1#
1,
#46600
b1001 q
b1001 r
b11111000 *
b11111000 +
#47000
0#
0,
#47500
b100011110 ;
b100011110 "
b1010 ?
1#
1,
#47600
b1010 q
b1010 r
b100011110 *
b100011110 +
#48000
0#
0,
#48500
b1011 ?
b101000100 ;
b101000100 "
1#
1,
#48600
b1011 q
b1011 r
b101000100 *
b101000100 +
#49000
0#
0,
#49500
b101101010 ;
b101101010 "
b1100 ?
1#
1,
#49600
b1100 q
b1100 r
b101101010 *
b101101010 +
#50000
0#
0,
#50500
b1101 ?
b101011000 ;
b101011000 "
1#
1,
#50600
b1101 q
b1101 r
b101011000 *
b101011000 +
#51000
0#
0,
#51500
b110001110 ;
b110001110 "
b1110 ?
1#
1,
#51600
b1110 q
b1110 r
b110001110 *
b110001110 +
#52000
0#
0,
#52500
b0 >
b1111 ?
b111000100 ;
b111000100 "
1#
1,
#52600
b1111 q
b1111 r
b111000100 *
b111000100 +
#53000
0#
0,
#53500
b111111010 ;
b111111010 "
b0 ?
b0 @
0!
1#
1,
#53600
b10000 q
b10000 r
b111111010 *
b111111010 +
